README.md
pyproject.toml
src/azurecost/__init__.py
src/azurecost/commands.py
src/azurecost/constants.py
src/azurecost/core.py
src/azurecost/date_util.py
src/azurecost/logger.py
src/azurecost.egg-info/PKG-INFO
src/azurecost.egg-info/SOURCES.txt
src/azurecost.egg-info/dependency_links.txt
src/azurecost.egg-info/entry_points.txt
src/azurecost.egg-info/requires.txt
src/azurecost.egg-info/top_level.txt
tests/test_commands.py