Metadata-Version: 2.1
Name: azurecost
Version: 0.4.0
Summary: Simple and easy command line to view azure costs.
Author-email: Hiroshi Toyama <toyama0919@gmail.com>
Project-URL: Homepage, https://github.com/toyama0919/azurecost
Keywords: azure,cost,tool,costmanagement
Classifier: Programming Language :: Python :: 3.8
Classifier: Programming Language :: Python :: 3.9
Classifier: Programming Language :: Python :: 3.10
Classifier: Programming Language :: Python :: 3.11
Classifier: Programming Language :: Python :: 3.12
Requires-Python: >=3.8
Requires-Dist: tabulate
Requires-Dist: click>=7.0
Requires-Dist: azure-identity
Requires-Dist: azure-mgmt-core
Requires-Dist: azure-mgmt-costmanagement
Requires-Dist: azure-mgmt-resource
Provides-Extra: test
Requires-Dist: tox; extra == "test"
